{
  "config": "tq_4bit",
  "bits": 4,
  "per_sample": {
    "jon__short": {
      "gen_time_sec": 6.876,
      "audio_duration_sec": 2.438,
      "rtf": 2.82,
      "success": true
    },
    "jon__medium": {
      "gen_time_sec": 20.41,
      "audio_duration_sec": 7.14,
      "rtf": 2.858,
      "success": true
    },
    "jon__long": {
      "gen_time_sec": 42.7,
      "audio_duration_sec": 14.187,
      "rtf": 3.01,
      "success": true
    },
    "laura__short": {
      "gen_time_sec": 7.097,
      "audio_duration_sec": 2.786,
      "rtf": 2.547,
      "success": true
    },
    "laura__medium": {
      "gen_time_sec": 23.595,
      "audio_duration_sec": 7.976,
      "rtf": 2.958,
      "success": true
    },
    "laura__long": {
      "gen_time_sec": 53.831,
      "audio_duration_sec": 17.821,
      "rtf": 3.021,
      "success": true
    },
    "gary__short": {
      "gen_time_sec": 6.023,
      "audio_duration_sec": 2.438,
      "rtf": 2.471,
      "success": true
    },
    "gary__medium": {
      "gen_time_sec": 30.958,
      "audio_duration_sec": 10.344,
      "rtf": 2.993,
      "success": true
    },
    "gary__long": {
      "gen_time_sec": 52.122,
      "audio_duration_sec": 16.974,
      "rtf": 3.071,
      "success": true
    }
  },
  "peak_gpu_bytes": 2862920192,
  "peak_gpu_gb": 2.86
}